emailconstructor/__init__.py
emailconstructor/email_constructor.py
emailconstructor-2.0.1.dist-info/LICENSE.txt
emailconstructor-2.0.1.dist-info/METADATA
emailconstructor-2.0.1.dist-info/WHEEL
emailconstructor-2.0.1.dist-info/top_level.txt
emailconstructor-2.0.1.dist-info/RECORD
