Metadata-Version: 2.1
Name: emailconstructor
Version: 2.0.1
Summary: Package to dynamically construct and send HTML-based emails.
Author: Erik Bierbrauer
Project-URL: Homepage, https://github.com/ebier92/emailconstructor
Project-URL: Bug Tracker, https://github.com/ebier92/emailconstructor/issues
Classifier: Programming Language :: Python :: 3
Classifier: License :: OSI Approved :: Apache Software License
Classifier: Operating System :: OS Independent
Requires-Python: >=3.12
License-File: LICENSE.txt
